ome2glancer/__init__.py
ome2glancer/__main__.py
ome2glancer/_version.py
ome2glancer/cli.py
ome2glancer/link_gen.py
ome2glancer/serve.py
ome2glancer-0.0.2.dist-info/licenses/LICENSE
ome2glancer-0.0.2.dist-info/METADATA
ome2glancer-0.0.2.dist-info/WHEEL
ome2glancer-0.0.2.dist-info/entry_points.txt
ome2glancer-0.0.2.dist-info/top_level.txt
ome2glancer-0.0.2.dist-info/RECORD
