Metadata-Version: 2.4
Name: ome2glancer
Version: 0.0.2
Summary: A package that generates neuroglancer links for ome-zarr files.
Author-email: Florian Aymanns <florian.aymanns@epfl.ch>
Maintainer-email: Florian Aymanns <flroian.aymanns@epfl.ch>
License: BSD 3-Clause License
Project-URL: Repository, https://github.com/EPFL-Center-for-Imaging/ome2glancer
Keywords: ome-zarr,neuroglancer
Classifier: Development Status :: 2 - Pre-Alpha
Classifier: Intended Audience :: Developers
Classifier: License :: OSI Approved :: BSD License
Classifier: Operating System :: OS Independent
Classifier: Programming Language :: Python
Classifier: Programming Language :: Python :: 3
Classifier: Programming Language :: Python :: 3 :: Only
Classifier: Programming Language :: Python :: 3.8
Classifier: Programming Language :: Python :: 3.9
Classifier: Programming Language :: Python :: 3.10
Classifier: Programming Language :: Python :: 3.11
Classifier: Programming Language :: Python :: 3.12
Classifier: Topic :: Scientific/Engineering
Requires-Python: >=3.8
License-File: LICENSE
Requires-Dist: typer
Requires-Dist: validators
Requires-Dist: neuroglancer
Requires-Dist: ome-zarr
Provides-Extra: test
Requires-Dist: tox; extra == "test"
Requires-Dist: pytest; extra == "test"
Requires-Dist: pytest-cov; extra == "test"
Provides-Extra: docs
Requires-Dist: pydata-sphinx-theme; extra == "docs"
Provides-Extra: all
Requires-Dist: ome2glancer[docs,test]; extra == "all"
Dynamic: license-file
